{
  "annotations": {
    "list": [
      {
        "builtIn": 1,
        "datasource": {
          "type": "grafana",
          "uid": "-- Grafana --"
        },
        "enable": true,
        "hide": true,
        "iconColor": "rgba(0, 211, 255, 1)",
        "name": "Annotations & Alerts",
        "target": {
          "limit": 100,
          "matchAny": false,
          "tags": [],
          "type": "dashboard"
        },
        "type": "dashboard"
      }
    ]
  },
  "editable": true,
  "fiscalYearStartMonth": 0,
  "graphTooltip": 0,
  "id": 35,
  "iteration": 1655847938135,
  "links": [],
  "liveNow": false,
  "panels": [
    {
      "collapsed": false,
      "gridPos": {
        "h": 1,
        "w": 24,
        "x": 0,
        "y": 0
      },
      "id": 16,
      "panels": [],
      "title": "Model Comparissons and General Summaries",
      "type": "row"
    },
    {
      "datasource": {
        "type": "prometheus",
        "uid": "prometheus"
      },
      "description": "The equation used is \n(mybag correct times)/(mybag correct times + mybag incorrect times)",
      "fieldConfig": {
        "defaults": {
          "color": {
            "mode": "palette-classic"
          },
          "custom": {
            "axisLabel": "Accuracy in %",
            "axisPlacement": "auto",
            "axisSoftMax": 100,
            "axisSoftMin": 0,
            "barAlignment": 0,
            "drawStyle": "line",
            "fillOpacity": 0,
            "gradientMode": "none",
            "hideFrom": {
              "legend": false,
              "tooltip": false,
              "viz": false
            },
            "lineInterpolation": "linear",
            "lineWidth": 1,
            "pointSize": 5,
            "scaleDistribution": {
              "type": "linear"
            },
            "showPoints": "auto",
            "spanNulls": false,
            "stacking": {
              "group": "A",
              "mode": "none"
            },
            "thresholdsStyle": {
              "mode": "off"
            }
          },
          "displayName": "prasko",
          "mappings": [],
          "thresholds": {
            "mode": "absolute",
            "steps": [
              {
                "color": "green",
                "value": null
              },
              {
                "color": "red",
                "value": 80
              }
            ]
          }
        },
        "overrides": []
      },
      "gridPos": {
        "h": 14,
        "w": 17,
        "x": 0,
        "y": 1
      },
      "id": 2,
      "options": {
        "legend": {
          "calcs": [],
          "displayMode": "hidden",
          "placement": "bottom"
        },
        "tooltip": {
          "mode": "single",
          "sort": "none"
        }
      },
      "targets": [
        {
          "datasource": {
            "type": "prometheus",
            "uid": "prometheus"
          },
          "editorMode": "code",
          "exemplar": false,
          "expr": "100*totalMybagCorrectTimes/(totalMybagCorrectTimes+totalMybagIncorrectTimes)",
          "hide": false,
          "instant": false,
          "legendFormat": "{{Bag-of-words}}",
          "range": true,
          "refId": "Mybag"
        },
        {
          "datasource": {
            "type": "prometheus",
            "uid": "prometheus"
          },
          "editorMode": "code",
          "exemplar": false,
          "expr": "100*totalTfidfCorrectTimes/(totalTfidfCorrectTimes+totalTfidfIncorrectTimes)",
          "hide": false,
          "instant": false,
          "legendFormat": "{{TF-IDF}}",
          "range": true,
          "refId": "Tfidf"
        }
      ],
      "title": "Accuracy Comparisson",
      "type": "timeseries"
    },
    {
      "datasource": {
        "type": "prometheus",
        "uid": "prometheus"
      },
      "fieldConfig": {
        "defaults": {
          "color": {
            "mode": "thresholds"
          },
          "custom": {
            "align": "auto",
            "displayMode": "auto",
            "inspect": false
          },
          "mappings": [],
          "thresholds": {
            "mode": "absolute",
            "steps": [
              {
                "color": "green",
                "value": null
              },
              {
                "color": "red",
                "value": 80
              }
            ]
          }
        },
        "overrides": []
      },
      "gridPos": {
        "h": 5,
        "w": 7,
        "x": 17,
        "y": 1
      },
      "id": 18,
      "options": {
        "footer": {
          "fields": "",
          "reducer": [
            "sum"
          ],
          "show": false
        },
        "showHeader": true,
        "sortBy": [
          {
            "desc": true,
            "displayName": "Value (sum)"
          }
        ]
      },
      "pluginVersion": "8.5.3",
      "targets": [
        {
          "datasource": {
            "type": "prometheus",
            "uid": "prometheus"
          },
          "editorMode": "code",
          "exemplar": false,
          "expr": "tagMetric",
          "format": "table",
          "instant": true,
          "range": false,
          "refId": "A"
        }
      ],
      "title": "Tag distribution over the three categories",
      "transformations": [
        {
          "id": "organize",
          "options": {
            "excludeByName": {
              "Time": true,
              "__name__": true,
              "container": true,
              "correctness": false,
              "endpoint": true,
              "instance": true,
              "job": true,
              "model": true,
              "namespace": true,
              "pod": true,
              "service": true,
              "tag_name": true
            },
            "indexByName": {},
            "renameByName": {}
          }
        },
        {
          "id": "groupBy",
          "options": {
            "fields": {
              "Value": {
                "aggregations": [
                  "sum"
                ],
                "operation": "aggregate"
              },
              "correctness": {
                "aggregations": [],
                "operation": "groupby"
              }
            }
          }
        }
      ],
      "type": "table"
    },
    {
      "datasource": {
        "type": "prometheus",
        "uid": "prometheus"
      },
      "fieldConfig": {
        "defaults": {
          "color": {
            "mode": "thresholds"
          },
          "custom": {
            "align": "auto",
            "displayMode": "auto",
            "inspect": false
          },
          "mappings": [],
          "thresholds": {
            "mode": "absolute",
            "steps": [
              {
                "color": "green",
                "value": null
              },
              {
                "color": "red",
                "value": 80
              }
            ]
          }
        },
        "overrides": []
      },
      "gridPos": {
        "h": 9,
        "w": 7,
        "x": 17,
        "y": 6
      },
      "id": 10,
      "options": {
        "footer": {
          "fields": "",
          "reducer": [
            "sum"
          ],
          "show": false
        },
        "showHeader": true,
        "sortBy": [
          {
            "desc": true,
            "displayName": "Value"
          }
        ]
      },
      "pluginVersion": "8.5.3",
      "targets": [
        {
          "datasource": {
            "type": "prometheus",
            "uid": "prometheus"
          },
          "editorMode": "builder",
          "exemplar": false,
          "expr": "tagMetric{correctness=\"missed\", model=\"both\"}",
          "format": "table",
          "instant": true,
          "interval": "",
          "legendFormat": "__auto",
          "range": false,
          "rawQuery": true,
          "refId": "A"
        }
      ],
      "title": "Amount of missed labels (included bty the user)",
      "transformations": [
        {
          "id": "organize",
          "options": {
            "excludeByName": {
              "Time": true,
              "__name__": true,
              "container": true,
              "correctness": false,
              "endpoint": true,
              "instance": true,
              "job": true,
              "model": true,
              "namespace": true,
              "pod": true,
              "service": true
            },
            "indexByName": {},
            "renameByName": {}
          }
        },
        {
          "id": "filterByValue",
          "options": {
            "filters": [
              {
                "config": {
                  "id": "lowerOrEqual",
                  "options": {
                    "value": 0
                  }
                },
                "fieldName": "Value"
              }
            ],
            "match": "all",
            "type": "exclude"
          }
        },
        {
          "disabled": true,
          "id": "groupBy",
          "options": {
            "fields": {
              "Value": {
                "aggregations": [
                  "sum"
                ],
                "operation": "aggregate"
              },
              "correctness": {
                "aggregations": [],
                "operation": "groupby"
              },
              "tag_name": {
                "aggregations": []
              }
            }
          }
        }
      ],
      "type": "table"
    },
    {
      "collapsed": false,
      "gridPos": {
        "h": 1,
        "w": 24,
        "x": 0,
        "y": 15
      },
      "id": 14,
      "panels": [],
      "title": "Bag-of-words Model",
      "type": "row"
    },
    {
      "datasource": {
        "type": "prometheus",
        "uid": "prometheus"
      },
      "description": "",
      "fieldConfig": {
        "defaults": {
          "color": {
            "mode": "palette-classic"
          },
          "custom": {
            "axisLabel": "",
            "axisPlacement": "auto",
            "barAlignment": 0,
            "drawStyle": "line",
            "fillOpacity": 0,
            "gradientMode": "none",
            "hideFrom": {
              "legend": false,
              "tooltip": false,
              "viz": false
            },
            "lineInterpolation": "linear",
            "lineWidth": 1,
            "pointSize": 5,
            "scaleDistribution": {
              "type": "linear"
            },
            "showPoints": "auto",
            "spanNulls": false,
            "stacking": {
              "group": "A",
              "mode": "none"
            },
            "thresholdsStyle": {
              "mode": "off"
            }
          },
          "mappings": [],
          "thresholds": {
            "mode": "absolute",
            "steps": [
              {
                "color": "green",
                "value": null
              },
              {
                "color": "red",
                "value": 80
              }
            ]
          }
        },
        "overrides": []
      },
      "gridPos": {
        "h": 8,
        "w": 12,
        "x": 0,
        "y": 16
      },
      "id": 6,
      "options": {
        "legend": {
          "calcs": [],
          "displayMode": "hidden",
          "placement": "bottom"
        },
        "tooltip": {
          "mode": "single",
          "sort": "none"
        }
      },
      "targets": [
        {
          "datasource": {
            "type": "prometheus",
            "uid": "prometheus"
          },
          "expr": "totalMybagCorrectTimes",
          "refId": "A"
        }
      ],
      "title": "Number of correct Bag-of-Words prediction",
      "type": "timeseries"
    },
    {
      "datasource": {
        "type": "prometheus",
        "uid": "prometheus"
      },
      "gridPos": {
        "h": 8,
        "w": 5,
        "x": 12,
        "y": 16
      },
      "id": 28,
      "options": {
        "content": "## Performance achived during training\n\n### Accuracy score:  0.36\n### Precision score:  0.81\n### Recall score:  0.56\n### F1 score:  0.66\n### Average precision score:  0.36",
        "mode": "markdown"
      },
      "pluginVersion": "8.5.3",
      "targets": [
        {
          "datasource": {
            "type": "prometheus",
            "uid": "prometheus"
          },
          "expr": "21",
          "refId": "A"
        },
        {
          "datasource": {
            "type": "prometheus",
            "uid": "prometheus"
          },
          "expr": "totalTfidfCorrectTimes",
          "hide": false,
          "refId": "B"
        }
      ],
      "title": "Training Stats Bag-of-Words",
      "type": "text"
    },
    {
      "datasource": {
        "type": "prometheus",
        "uid": "prometheus"
      },
      "fieldConfig": {
        "defaults": {
          "color": {
            "mode": "thresholds"
          },
          "custom": {
            "align": "auto",
            "displayMode": "auto",
            "inspect": false
          },
          "mappings": [],
          "thresholds": {
            "mode": "absolute",
            "steps": [
              {
                "color": "green",
                "value": null
              },
              {
                "color": "red",
                "value": 80
              }
            ]
          }
        },
        "overrides": []
      },
      "gridPos": {
        "h": 16,
        "w": 7,
        "x": 17,
        "y": 16
      },
      "id": 23,
      "options": {
        "footer": {
          "fields": "",
          "reducer": [
            "sum"
          ],
          "show": false
        },
        "frameIndex": 1,
        "showHeader": true
      },
      "pluginVersion": "8.5.3",
      "targets": [
        {
          "datasource": {
            "type": "prometheus",
            "uid": "prometheus"
          },
          "editorMode": "builder",
          "exemplar": false,
          "expr": "tagMetric{correctness=\"correct\"}",
          "format": "table",
          "instant": true,
          "range": false,
          "rawQuery": false,
          "refId": "A"
        },
        {
          "datasource": {
            "type": "prometheus",
            "uid": "prometheus"
          },
          "editorMode": "builder",
          "exemplar": false,
          "expr": "tagMetric{correctness=\"incorrect\"}",
          "format": "table",
          "hide": false,
          "instant": true,
          "range": false,
          "refId": "B"
        }
      ],
      "title": "Tags distribution (Bag-of-words)",
      "transformations": [
        {
          "id": "filterByValue",
          "options": {
            "filters": [
              {
                "config": {
                  "id": "equal",
                  "options": {
                    "value": "Bag-of-words"
                  }
                },
                "fieldName": "model"
              }
            ],
            "match": "all",
            "type": "include"
          }
        },
        {
          "id": "seriesToColumns",
          "options": {
            "byField": "tag_name"
          }
        },
        {
          "id": "organize",
          "options": {
            "excludeByName": {
              "Time 1": true,
              "Time 2": true,
              "Value #A": false,
              "__name__ 1": true,
              "__name__ 2": true,
              "container 1": true,
              "container 2": true,
              "correctness 1": true,
              "correctness 2": true,
              "endpoint 1": true,
              "endpoint 2": true,
              "instance 1": true,
              "instance 2": true,
              "job 1": true,
              "job 2": true,
              "model 1": false,
              "namespace 1": true,
              "namespace 2": true,
              "pod 1": true,
              "pod 2": true,
              "service 1": true,
              "service 2": true
            },
            "indexByName": {},
            "renameByName": {}
          }
        },
        {
          "disabled": true,
          "id": "filterByValue",
          "options": {
            "filters": [
              {
                "config": {
                  "id": "equal",
                  "options": {
                    "value": "Bag-of-words"
                  }
                },
                "fieldName": "model 1"
              },
              {
                "config": {
                  "id": "equal",
                  "options": {
                    "value": "Bag-of-words"
                  }
                },
                "fieldName": "model 2"
              }
            ],
            "match": "all",
            "type": "include"
          }
        },
        {
          "id": "organize",
          "options": {
            "excludeByName": {
              "model 1": true,
              "model 2": true
            },
            "indexByName": {},
            "renameByName": {
              "Value #A": "Correct",
              "Value #B": "Incorrect "
            }
          }
        },
        {
          "id": "filterByValue",
          "options": {
            "filters": [
              {
                "config": {
                  "id": "greater",
                  "options": {
                    "value": 0
                  }
                },
                "fieldName": "Correct"
              },
              {
                "config": {
                  "id": "greater",
                  "options": {
                    "value": 0
                  }
                },
                "fieldName": "Incorrect "
              }
            ],
            "match": "any",
            "type": "include"
          }
        }
      ],
      "type": "table"
    },
    {
      "datasource": {
        "type": "prometheus",
        "uid": "prometheus"
      },
      "fieldConfig": {
        "defaults": {
          "color": {
            "mode": "thresholds"
          },
          "mappings": [],
          "thresholds": {
            "mode": "absolute",
            "steps": [
              {
                "color": "green",
                "value": null
              },
              {
                "color": "red",
                "value": 80
              }
            ]
          }
        },
        "overrides": []
      },
      "gridPos": {
        "h": 8,
        "w": 4,
        "x": 0,
        "y": 24
      },
      "id": 35,
      "options": {
        "orientation": "auto",
        "reduceOptions": {
          "calcs": [
            "lastNotNull"
          ],
          "fields": "",
          "values": false
        },
        "showThresholdLabels": false,
        "showThresholdMarkers": true
      },
      "pluginVersion": "8.5.3",
      "targets": [
        {
          "datasource": {
            "type": "prometheus",
            "uid": "prometheus"
          },
          "expr": "totalMybagCorrectTimes/(totalMybagCorrectTimes+totalMybagIncorrectTimes)",
          "refId": "A"
        }
      ],
      "title": "Accuracy",
      "type": "gauge"
    },
    {
      "datasource": {
        "type": "prometheus",
        "uid": "prometheus"
      },
      "description": "The equation used is \n(mybag correct times)/(mybag correct times + mybag incorrect times)",
      "fieldConfig": {
        "defaults": {
          "color": {
            "mode": "palette-classic"
          },
          "custom": {
            "axisLabel": "",
            "axisPlacement": "auto",
            "axisSoftMax": 1,
            "axisSoftMin": 0,
            "barAlignment": 0,
            "drawStyle": "line",
            "fillOpacity": 0,
            "gradientMode": "none",
            "hideFrom": {
              "legend": false,
              "tooltip": false,
              "viz": false
            },
            "lineInterpolation": "linear",
            "lineWidth": 1,
            "pointSize": 5,
            "scaleDistribution": {
              "type": "linear"
            },
            "showPoints": "auto",
            "spanNulls": false,
            "stacking": {
              "group": "A",
              "mode": "none"
            },
            "thresholdsStyle": {
              "mode": "off"
            }
          },
          "mappings": [],
          "thresholds": {
            "mode": "absolute",
            "steps": [
              {
                "color": "green",
                "value": null
              },
              {
                "color": "red",
                "value": 80
              }
            ]
          }
        },
        "overrides": []
      },
      "gridPos": {
        "h": 8,
        "w": 13,
        "x": 4,
        "y": 24
      },
      "id": 19,
      "options": {
        "legend": {
          "calcs": [],
          "displayMode": "hidden",
          "placement": "bottom"
        },
        "tooltip": {
          "mode": "single",
          "sort": "none"
        }
      },
      "targets": [
        {
          "datasource": {
            "type": "prometheus",
            "uid": "prometheus"
          },
          "expr": "totalMybagCorrectTimes/(totalMybagCorrectTimes+totalMybagIncorrectTimes)",
          "refId": "A"
        }
      ],
      "title": "Accuracy of Bag-of-words Classifier",
      "type": "timeseries"
    },
    {
      "datasource": {
        "type": "prometheus",
        "uid": "prometheus"
      },
      "fieldConfig": {
        "defaults": {
          "color": {
            "mode": "thresholds"
          },
          "mappings": [],
          "thresholds": {
            "mode": "absolute",
            "steps": [
              {
                "color": "green",
                "value": null
              },
              {
                "color": "red",
                "value": 80
              }
            ]
          }
        },
        "overrides": []
      },
      "gridPos": {
        "h": 8,
        "w": 4,
        "x": 0,
        "y": 32
      },
      "id": 36,
      "options": {
        "orientation": "auto",
        "reduceOptions": {
          "calcs": [
            "lastNotNull"
          ],
          "fields": "",
          "values": false
        },
        "showThresholdLabels": false,
        "showThresholdMarkers": true
      },
      "pluginVersion": "8.5.3",
      "targets": [
        {
          "datasource": {
            "type": "prometheus",
            "uid": "prometheus"
          },
          "expr": "mybagPrecision",
          "refId": "A"
        }
      ],
      "title": "Precision",
      "type": "gauge"
    },
    {
      "datasource": {
        "type": "prometheus",
        "uid": "prometheus"
      },
      "description": "The equation used is \n(mybag correct times)/(mybag correct times + mybag incorrect times)",
      "fieldConfig": {
        "defaults": {
          "color": {
            "mode": "palette-classic"
          },
          "custom": {
            "axisLabel": "",
            "axisPlacement": "auto",
            "barAlignment": 0,
            "drawStyle": "line",
            "fillOpacity": 0,
            "gradientMode": "none",
            "hideFrom": {
              "legend": false,
              "tooltip": false,
              "viz": false
            },
            "lineInterpolation": "linear",
            "lineWidth": 1,
            "pointSize": 5,
            "scaleDistribution": {
              "type": "linear"
            },
            "showPoints": "auto",
            "spanNulls": false,
            "stacking": {
              "group": "A",
              "mode": "none"
            },
            "thresholdsStyle": {
              "mode": "off"
            }
          },
          "mappings": [],
          "thresholds": {
            "mode": "absolute",
            "steps": [
              {
                "color": "green",
                "value": null
              },
              {
                "color": "red",
                "value": 80
              }
            ]
          }
        },
        "overrides": []
      },
      "gridPos": {
        "h": 8,
        "w": 13,
        "x": 4,
        "y": 32
      },
      "id": 39,
      "options": {
        "legend": {
          "calcs": [],
          "displayMode": "hidden",
          "placement": "bottom"
        },
        "tooltip": {
          "mode": "single",
          "sort": "none"
        }
      },
      "targets": [
        {
          "datasource": {
            "type": "prometheus",
            "uid": "prometheus"
          },
          "expr": "mybagPrecision",
          "refId": "A"
        }
      ],
      "title": "Precision history of Bag-of-words Classifier",
      "type": "timeseries"
    },
    {
      "datasource": {
        "type": "prometheus",
        "uid": "prometheus"
      },
      "fieldConfig": {
        "defaults": {
          "color": {
            "mode": "thresholds"
          },
          "mappings": [],
          "thresholds": {
            "mode": "absolute",
            "steps": [
              {
                "color": "green",
                "value": null
              },
              {
                "color": "red",
                "value": 80
              }
            ]
          }
        },
        "overrides": []
      },
      "gridPos": {
        "h": 8,
        "w": 4,
        "x": 0,
        "y": 40
      },
      "id": 37,
      "options": {
        "orientation": "auto",
        "reduceOptions": {
          "calcs": [
            "lastNotNull"
          ],
          "fields": "",
          "values": false
        },
        "showThresholdLabels": false,
        "showThresholdMarkers": true
      },
      "pluginVersion": "8.5.3",
      "targets": [
        {
          "datasource": {
            "type": "prometheus",
            "uid": "prometheus"
          },
          "expr": "mybagRecall",
          "refId": "A"
        }
      ],
      "title": "Recall",
      "type": "gauge"
    },
    {
      "datasource": {
        "type": "prometheus",
        "uid": "prometheus"
      },
      "description": "The equation used is \n(mybag correct times)/(mybag correct times + mybag incorrect times)",
      "fieldConfig": {
        "defaults": {
          "color": {
            "mode": "palette-classic"
          },
          "custom": {
            "axisLabel": "",
            "axisPlacement": "auto",
            "barAlignment": 0,
            "drawStyle": "line",
            "fillOpacity": 0,
            "gradientMode": "none",
            "hideFrom": {
              "legend": false,
              "tooltip": false,
              "viz": false
            },
            "lineInterpolation": "linear",
            "lineWidth": 1,
            "pointSize": 5,
            "scaleDistribution": {
              "type": "linear"
            },
            "showPoints": "auto",
            "spanNulls": false,
            "stacking": {
              "group": "A",
              "mode": "none"
            },
            "thresholdsStyle": {
              "mode": "off"
            }
          },
          "mappings": [],
          "thresholds": {
            "mode": "absolute",
            "steps": [
              {
                "color": "green",
                "value": null
              },
              {
                "color": "red",
                "value": 80
              }
            ]
          }
        },
        "overrides": []
      },
      "gridPos": {
        "h": 8,
        "w": 13,
        "x": 4,
        "y": 40
      },
      "id": 40,
      "options": {
        "legend": {
          "calcs": [],
          "displayMode": "hidden",
          "placement": "bottom"
        },
        "tooltip": {
          "mode": "single",
          "sort": "none"
        }
      },
      "targets": [
        {
          "datasource": {
            "type": "prometheus",
            "uid": "prometheus"
          },
          "expr": "mybagRecall",
          "refId": "A"
        }
      ],
      "title": "Recall history of Bag-of-words Classifier",
      "type": "timeseries"
    },
    {
      "datasource": {
        "type": "prometheus",
        "uid": "prometheus"
      },
      "fieldConfig": {
        "defaults": {
          "color": {
            "mode": "thresholds"
          },
          "mappings": [],
          "thresholds": {
            "mode": "absolute",
            "steps": [
              {
                "color": "green",
                "value": null
              },
              {
                "color": "red",
                "value": 80
              }
            ]
          }
        },
        "overrides": []
      },
      "gridPos": {
        "h": 8,
        "w": 4,
        "x": 0,
        "y": 48
      },
      "id": 38,
      "options": {
        "orientation": "auto",
        "reduceOptions": {
          "calcs": [
            "lastNotNull"
          ],
          "fields": "",
          "values": false
        },
        "showThresholdLabels": false,
        "showThresholdMarkers": true
      },
      "pluginVersion": "8.5.3",
      "targets": [
        {
          "datasource": {
            "type": "prometheus",
            "uid": "prometheus"
          },
          "expr": "mybagF1",
          "refId": "A"
        }
      ],
      "title": "F1 score",
      "type": "gauge"
    },
    {
      "datasource": {
        "type": "prometheus",
        "uid": "prometheus"
      },
      "description": "The equation used is \n(mybag correct times)/(mybag correct times + mybag incorrect times)",
      "fieldConfig": {
        "defaults": {
          "color": {
            "mode": "palette-classic"
          },
          "custom": {
            "axisLabel": "",
            "axisPlacement": "auto",
            "barAlignment": 0,
            "drawStyle": "line",
            "fillOpacity": 0,
            "gradientMode": "none",
            "hideFrom": {
              "legend": false,
              "tooltip": false,
              "viz": false
            },
            "lineInterpolation": "linear",
            "lineWidth": 1,
            "pointSize": 5,
            "scaleDistribution": {
              "type": "linear"
            },
            "showPoints": "auto",
            "spanNulls": false,
            "stacking": {
              "group": "A",
              "mode": "none"
            },
            "thresholdsStyle": {
              "mode": "off"
            }
          },
          "mappings": [],
          "thresholds": {
            "mode": "absolute",
            "steps": [
              {
                "color": "green",
                "value": null
              },
              {
                "color": "red",
                "value": 80
              }
            ]
          }
        },
        "overrides": []
      },
      "gridPos": {
        "h": 8,
        "w": 13,
        "x": 4,
        "y": 48
      },
      "id": 41,
      "options": {
        "legend": {
          "calcs": [],
          "displayMode": "hidden",
          "placement": "bottom"
        },
        "tooltip": {
          "mode": "single",
          "sort": "none"
        }
      },
      "targets": [
        {
          "datasource": {
            "type": "prometheus",
            "uid": "prometheus"
          },
          "expr": "mybagF1",
          "refId": "A"
        }
      ],
      "title": "F1 score history of Bag-of-words Classifier",
      "type": "timeseries"
    },
    {
      "collapsed": true,
      "gridPos": {
        "h": 1,
        "w": 24,
        "x": 0,
        "y": 56
      },
      "id": 12,
      "panels": [
        {
          "datasource": {
            "type": "prometheus",
            "uid": "prometheus"
          },
          "fieldConfig": {
            "defaults": {
              "color": {
                "mode": "palette-classic"
              },
              "custom": {
                "axisLabel": "",
                "axisPlacement": "auto",
                "barAlignment": 0,
                "drawStyle": "line",
                "fillOpacity": 0,
                "gradientMode": "none",
                "hideFrom": {
                  "legend": false,
                  "tooltip": false,
                  "viz": false
                },
                "lineInterpolation": "linear",
                "lineWidth": 1,
                "pointSize": 5,
                "scaleDistribution": {
                  "type": "linear"
                },
                "showPoints": "auto",
                "spanNulls": false,
                "stacking": {
                  "group": "A",
                  "mode": "none"
                },
                "thresholdsStyle": {
                  "mode": "off"
                }
              },
              "displayName": "nasko",
              "mappings": [],
              "thresholds": {
                "mode": "absolute",
                "steps": [
                  {
                    "color": "green",
                    "value": null
                  },
                  {
                    "color": "red",
                    "value": 80
                  }
                ]
              }
            },
            "overrides": []
          },
          "gridPos": {
            "h": 8,
            "w": 12,
            "x": 0,
            "y": 17
          },
          "id": 8,
          "options": {
            "legend": {
              "calcs": [],
              "displayMode": "hidden",
              "placement": "bottom"
            },
            "tooltip": {
              "mode": "single",
              "sort": "none"
            }
          },
          "pluginVersion": "8.5.3",
          "targets": [
            {
              "datasource": {
                "type": "prometheus",
                "uid": "prometheus"
              },
              "expr": "totalTfidfCorrectTimes",
              "refId": "A"
            }
          ],
          "title": "Number of Correct TFIDF Prediction",
          "type": "timeseries"
        },
        {
          "datasource": {
            "type": "prometheus",
            "uid": "prometheus"
          },
          "gridPos": {
            "h": 8,
            "w": 5,
            "x": 12,
            "y": 17
          },
          "id": 27,
          "options": {
            "content": "## Performance achieved during training\n\n### Accuracy score:  0.37\n### Precision score:  0.83\n### Recall score:  0.55\n### F1 score:  0.65\n### Average precision score:  0.35",
            "mode": "markdown"
          },
          "pluginVersion": "8.5.3",
          "targets": [
            {
              "datasource": {
                "type": "prometheus",
                "uid": "prometheus"
              },
              "expr": "21",
              "refId": "A"
            },
            {
              "datasource": {
                "type": "prometheus",
                "uid": "prometheus"
              },
              "expr": "totalTfidfCorrectTimes",
              "hide": false,
              "refId": "B"
            }
          ],
          "title": "Training Stats TF-IDF",
          "type": "text"
        },
        {
          "datasource": {
            "type": "prometheus",
            "uid": "prometheus"
          },
          "fieldConfig": {
            "defaults": {
              "color": {
                "mode": "thresholds"
              },
              "custom": {
                "align": "auto",
                "displayMode": "auto",
                "inspect": false
              },
              "mappings": [],
              "thresholds": {
                "mode": "absolute",
                "steps": [
                  {
                    "color": "green",
                    "value": null
                  },
                  {
                    "color": "red",
                    "value": 80
                  }
                ]
              }
            },
            "overrides": []
          },
          "gridPos": {
            "h": 16,
            "w": 7,
            "x": 17,
            "y": 17
          },
          "id": 21,
          "options": {
            "footer": {
              "fields": "",
              "reducer": [
                "sum"
              ],
              "show": false
            },
            "showHeader": true,
            "sortBy": [
              {
                "desc": true,
                "displayName": "Incorrect"
              }
            ]
          },
          "pluginVersion": "8.5.3",
          "targets": [
            {
              "datasource": {
                "type": "prometheus",
                "uid": "prometheus"
              },
              "editorMode": "builder",
              "exemplar": false,
              "expr": "tagMetric{correctness=\"correct\"}",
              "format": "table",
              "instant": true,
              "range": false,
              "refId": "A"
            },
            {
              "datasource": {
                "type": "prometheus",
                "uid": "prometheus"
              },
              "editorMode": "builder",
              "exemplar": false,
              "expr": "tagMetric{correctness=\"incorrect\"}",
              "format": "table",
              "hide": false,
              "instant": true,
              "range": false,
              "refId": "B"
            }
          ],
          "title": "Tag distribution (TF-IDF)",
          "transformations": [
            {
              "id": "filterByValue",
              "options": {
                "filters": [
                  {
                    "config": {
                      "id": "equal",
                      "options": {
                        "value": "TF-IDF"
                      }
                    },
                    "fieldName": "model"
                  }
                ],
                "match": "all",
                "type": "include"
              }
            },
            {
              "id": "seriesToColumns",
              "options": {
                "byField": "tag_name"
              }
            },
            {
              "id": "organize",
              "options": {
                "excludeByName": {
                  "Time": true,
                  "Time 1": true,
                  "Time 2": true,
                  "__name__": true,
                  "__name__ 1": true,
                  "__name__ 2": true,
                  "container": true,
                  "container 1": true,
                  "container 2": true,
                  "correctness 1": true,
                  "correctness 2": true,
                  "endpoint": true,
                  "endpoint 1": true,
                  "endpoint 2": true,
                  "instance": true,
                  "instance 1": true,
                  "instance 2": true,
                  "job": true,
                  "job 1": true,
                  "job 2": true,
                  "model": false,
                  "model 1": true,
                  "model 2": true,
                  "namespace": true,
                  "namespace 1": true,
                  "namespace 2": true,
                  "pod": true,
                  "pod 1": true,
                  "pod 2": true,
                  "service": true,
                  "service 1": true,
                  "service 2": true,
                  "tag_name": false
                },
                "indexByName": {},
                "renameByName": {
                  "Value": "Correct",
                  "Value #A": "Correct",
                  "Value #B": "Incorrect",
                  "tag_name": ""
                }
              }
            },
            {
              "id": "filterByValue",
              "options": {
                "filters": [
                  {
                    "config": {
                      "id": "greater",
                      "options": {
                        "value": 0
                      }
                    },
                    "fieldName": "Correct"
                  },
                  {
                    "config": {
                      "id": "greater",
                      "options": {
                        "value": 0
                      }
                    },
                    "fieldName": "Incorrect"
                  }
                ],
                "match": "any",
                "type": "include"
              }
            }
          ],
          "type": "table"
        },
        {
          "datasource": {
            "type": "prometheus",
            "uid": "prometheus"
          },
          "fieldConfig": {
            "defaults": {
              "color": {
                "mode": "thresholds"
              },
              "mappings": [],
              "thresholds": {
                "mode": "absolute",
                "steps": [
                  {
                    "color": "green",
                    "value": null
                  },
                  {
                    "color": "red",
                    "value": 80
                  }
                ]
              }
            },
            "overrides": []
          },
          "gridPos": {
            "h": 8,
            "w": 4,
            "x": 0,
            "y": 25
          },
          "id": 25,
          "options": {
            "orientation": "auto",
            "reduceOptions": {
              "calcs": [
                "lastNotNull"
              ],
              "fields": "",
              "values": false
            },
            "showThresholdLabels": false,
            "showThresholdMarkers": true
          },
          "pluginVersion": "8.5.3",
          "targets": [
            {
              "datasource": {
                "type": "prometheus",
                "uid": "prometheus"
              },
              "expr": "totalTfidfCorrectTimes/(totalTfidfCorrectTimes+totalTfidfIncorrectTimes)",
              "refId": "A"
            }
          ],
          "title": "Accuracy",
          "type": "gauge"
        },
        {
          "datasource": {
            "type": "prometheus",
            "uid": "prometheus"
          },
          "description": "The equation used to calculate the accuracy of tfidf classifier is (tfidf correct times)/(tfidf correct times + tfidf incorrect times)",
          "fieldConfig": {
            "defaults": {
              "color": {
                "mode": "palette-classic"
              },
              "custom": {
                "axisLabel": "",
                "axisPlacement": "auto",
                "barAlignment": 0,
                "drawStyle": "line",
                "fillOpacity": 0,
                "gradientMode": "none",
                "hideFrom": {
                  "legend": false,
                  "tooltip": false,
                  "viz": false
                },
                "lineInterpolation": "linear",
                "lineWidth": 1,
                "pointSize": 5,
                "scaleDistribution": {
                  "type": "linear"
                },
                "showPoints": "auto",
                "spanNulls": false,
                "stacking": {
                  "group": "A",
                  "mode": "none"
                },
                "thresholdsStyle": {
                  "mode": "off"
                }
              },
              "mappings": [],
              "thresholds": {
                "mode": "absolute",
                "steps": [
                  {
                    "color": "green",
                    "value": null
                  },
                  {
                    "color": "red",
                    "value": 80
                  }
                ]
              }
            },
            "overrides": [
              {
                "__systemRef": "hideSeriesFrom",
                "matcher": {
                  "id": "byNames",
                  "options": {
                    "mode": "exclude",
                    "names": [
                      "{container=\"tag-web\", endpoint=\"8080\", instance=\"172.17.0.14:8080\", job=\"tag-web-svc\", namespace=\"default\", pod=\"tag-web-depl-7544dd846c-ztb6w\", service=\"tag-web-svc\"}"
                    ],
                    "prefix": "All except:",
                    "readOnly": true
                  }
                },
                "properties": [
                  {
                    "id": "custom.hideFrom",
                    "value": {
                      "legend": false,
                      "tooltip": false,
                      "viz": true
                    }
                  }
                ]
              }
            ]
          },
          "gridPos": {
            "h": 8,
            "w": 13,
            "x": 4,
            "y": 25
          },
          "id": 4,
          "options": {
            "legend": {
              "calcs": [],
              "displayMode": "hidden",
              "placement": "bottom"
            },
            "tooltip": {
              "mode": "single",
              "sort": "none"
            }
          },
          "targets": [
            {
              "datasource": {
                "type": "prometheus",
                "uid": "prometheus"
              },
              "expr": "totalTfidfCorrectTimes/(totalTfidfCorrectTimes+totalTfidfIncorrectTimes)",
              "refId": "A"
            }
          ],
          "title": "Accuracy history of TF-IDF Classifier",
          "type": "timeseries"
        },
        {
          "datasource": {
            "type": "prometheus",
            "uid": "prometheus"
          },
          "fieldConfig": {
            "defaults": {
              "color": {
                "mode": "thresholds"
              },
              "mappings": [],
              "thresholds": {
                "mode": "absolute",
                "steps": [
                  {
                    "color": "green",
                    "value": null
                  },
                  {
                    "color": "red",
                    "value": 80
                  }
                ]
              }
            },
            "overrides": []
          },
          "gridPos": {
            "h": 8,
            "w": 4,
            "x": 0,
            "y": 33
          },
          "id": 29,
          "options": {
            "orientation": "auto",
            "reduceOptions": {
              "calcs": [
                "lastNotNull"
              ],
              "fields": "",
              "values": false
            },
            "showThresholdLabels": false,
            "showThresholdMarkers": true
          },
          "pluginVersion": "8.5.3",
          "targets": [
            {
              "datasource": {
                "type": "prometheus",
                "uid": "prometheus"
              },
              "expr": "tfidfPrecision",
              "refId": "A"
            }
          ],
          "title": "Precision",
          "type": "gauge"
        },
        {
          "datasource": {
            "type": "prometheus",
            "uid": "prometheus"
          },
          "description": "The equation used to calculate the accuracy of tfidf classifier is (tfidf correct times)/(tfidf correct times + tfidf incorrect times)",
          "fieldConfig": {
            "defaults": {
              "color": {
                "mode": "palette-classic"
              },
              "custom": {
                "axisLabel": "",
                "axisPlacement": "auto",
                "barAlignment": 0,
                "drawStyle": "line",
                "fillOpacity": 0,
                "gradientMode": "none",
                "hideFrom": {
                  "legend": false,
                  "tooltip": false,
                  "viz": false
                },
                "lineInterpolation": "linear",
                "lineWidth": 1,
                "pointSize": 5,
                "scaleDistribution": {
                  "type": "linear"
                },
                "showPoints": "auto",
                "spanNulls": false,
                "stacking": {
                  "group": "A",
                  "mode": "none"
                },
                "thresholdsStyle": {
                  "mode": "off"
                }
              },
              "mappings": [],
              "thresholds": {
                "mode": "absolute",
                "steps": [
                  {
                    "color": "green",
                    "value": null
                  },
                  {
                    "color": "red",
                    "value": 80
                  }
                ]
              }
            },
            "overrides": []
          },
          "gridPos": {
            "h": 8,
            "w": 13,
            "x": 4,
            "y": 33
          },
          "id": 30,
          "options": {
            "legend": {
              "calcs": [],
              "displayMode": "list",
              "placement": "bottom"
            },
            "tooltip": {
              "mode": "single",
              "sort": "none"
            }
          },
          "targets": [
            {
              "datasource": {
                "type": "prometheus",
                "uid": "prometheus"
              },
              "expr": "tfidfPrecision",
              "refId": "A"
            }
          ],
          "title": "Precision history of TF-IDF Classifier",
          "type": "timeseries"
        },
        {
          "datasource": {
            "type": "prometheus",
            "uid": "prometheus"
          },
          "fieldConfig": {
            "defaults": {
              "color": {
                "mode": "thresholds"
              },
              "mappings": [],
              "thresholds": {
                "mode": "absolute",
                "steps": [
                  {
                    "color": "green",
                    "value": null
                  },
                  {
                    "color": "red",
                    "value": 80
                  }
                ]
              }
            },
            "overrides": []
          },
          "gridPos": {
            "h": 8,
            "w": 4,
            "x": 0,
            "y": 41
          },
          "id": 31,
          "options": {
            "orientation": "auto",
            "reduceOptions": {
              "calcs": [
                "lastNotNull"
              ],
              "fields": "",
              "values": false
            },
            "showThresholdLabels": false,
            "showThresholdMarkers": true
          },
          "pluginVersion": "8.5.3",
          "targets": [
            {
              "datasource": {
                "type": "prometheus",
                "uid": "prometheus"
              },
              "expr": "tfidfRecall",
              "refId": "A"
            }
          ],
          "title": "Recall",
          "type": "gauge"
        },
        {
          "datasource": {
            "type": "prometheus",
            "uid": "prometheus"
          },
          "description": "The equation used to calculate the accuracy of tfidf classifier is (tfidf correct times)/(tfidf correct times + tfidf incorrect times)",
          "fieldConfig": {
            "defaults": {
              "color": {
                "mode": "palette-classic"
              },
              "custom": {
                "axisLabel": "",
                "axisPlacement": "auto",
                "barAlignment": 0,
                "drawStyle": "line",
                "fillOpacity": 0,
                "gradientMode": "none",
                "hideFrom": {
                  "legend": false,
                  "tooltip": false,
                  "viz": false
                },
                "lineInterpolation": "linear",
                "lineWidth": 1,
                "pointSize": 5,
                "scaleDistribution": {
                  "type": "linear"
                },
                "showPoints": "auto",
                "spanNulls": false,
                "stacking": {
                  "group": "A",
                  "mode": "none"
                },
                "thresholdsStyle": {
                  "mode": "off"
                }
              },
              "mappings": [],
              "thresholds": {
                "mode": "absolute",
                "steps": [
                  {
                    "color": "green",
                    "value": null
                  },
                  {
                    "color": "red",
                    "value": 80
                  }
                ]
              }
            },
            "overrides": []
          },
          "gridPos": {
            "h": 8,
            "w": 13,
            "x": 4,
            "y": 41
          },
          "id": 32,
          "options": {
            "legend": {
              "calcs": [],
              "displayMode": "list",
              "placement": "bottom"
            },
            "tooltip": {
              "mode": "single",
              "sort": "none"
            }
          },
          "targets": [
            {
              "datasource": {
                "type": "prometheus",
                "uid": "prometheus"
              },
              "expr": "tfidfRecall",
              "refId": "A"
            }
          ],
          "title": "Recall history of TF-IDF Classifier",
          "type": "timeseries"
        },
        {
          "datasource": {
            "type": "prometheus",
            "uid": "prometheus"
          },
          "fieldConfig": {
            "defaults": {
              "color": {
                "mode": "thresholds"
              },
              "mappings": [],
              "thresholds": {
                "mode": "absolute",
                "steps": [
                  {
                    "color": "green",
                    "value": null
                  },
                  {
                    "color": "red",
                    "value": 80
                  }
                ]
              }
            },
            "overrides": []
          },
          "gridPos": {
            "h": 8,
            "w": 4,
            "x": 0,
            "y": 49
          },
          "id": 33,
          "options": {
            "orientation": "auto",
            "reduceOptions": {
              "calcs": [
                "lastNotNull"
              ],
              "fields": "",
              "values": false
            },
            "showThresholdLabels": false,
            "showThresholdMarkers": true
          },
          "pluginVersion": "8.5.3",
          "targets": [
            {
              "datasource": {
                "type": "prometheus",
                "uid": "prometheus"
              },
              "expr": "tfidfF1",
              "refId": "A"
            }
          ],
          "title": "F1 score",
          "type": "gauge"
        },
        {
          "datasource": {
            "type": "prometheus",
            "uid": "prometheus"
          },
          "description": "The equation used to calculate the accuracy of tfidf classifier is (tfidf correct times)/(tfidf correct times + tfidf incorrect times)",
          "fieldConfig": {
            "defaults": {
              "color": {
                "mode": "palette-classic"
              },
              "custom": {
                "axisLabel": "",
                "axisPlacement": "auto",
                "barAlignment": 0,
                "drawStyle": "line",
                "fillOpacity": 0,
                "gradientMode": "none",
                "hideFrom": {
                  "legend": false,
                  "tooltip": false,
                  "viz": false
                },
                "lineInterpolation": "linear",
                "lineWidth": 1,
                "pointSize": 5,
                "scaleDistribution": {
                  "type": "linear"
                },
                "showPoints": "auto",
                "spanNulls": false,
                "stacking": {
                  "group": "A",
                  "mode": "none"
                },
                "thresholdsStyle": {
                  "mode": "off"
                }
              },
              "mappings": [],
              "thresholds": {
                "mode": "absolute",
                "steps": [
                  {
                    "color": "green",
                    "value": null
                  },
                  {
                    "color": "red",
                    "value": 80
                  }
                ]
              }
            },
            "overrides": []
          },
          "gridPos": {
            "h": 8,
            "w": 13,
            "x": 4,
            "y": 49
          },
          "id": 34,
          "options": {
            "legend": {
              "calcs": [],
              "displayMode": "list",
              "placement": "bottom"
            },
            "tooltip": {
              "mode": "single",
              "sort": "none"
            }
          },
          "targets": [
            {
              "datasource": {
                "type": "prometheus",
                "uid": "prometheus"
              },
              "expr": "tfidfF1",
              "refId": "A"
            }
          ],
          "title": "F1 score history of TF-IDF Classifier",
          "type": "timeseries"
        }
      ],
      "title": "TF-IDF Model",
      "type": "row"
    }
  ],
  "refresh": false,
  "schemaVersion": 36,
  "style": "dark",
  "tags": [],
  "templating": {
    "list": [
      {
        "datasource": {
          "type": "prometheus",
          "uid": "prometheus"
        },
        "filters": [],
        "hide": 0,
        "name": "Filters",
        "skipUrlSync": false,
        "type": "adhoc"
      }
    ]
  },
  "time": {
    "from": "now-5m",
    "to": "now"
  },
  "timepicker": {},
  "timezone": "",
  "title": "Dashboardv5",
  "uid": "zIq5Vmj885",
  "version": 1,
  "weekStart": ""
}